data/__init__.py
data/message/DataMessageProcessor.py
data/message/__init__.py
data/payload/DataPayloadProcessor.py
data/payload/__init__.py
data/websocket/DataWebSocket.py
data/websocket/WebSocketRunner.py
data/websocket/__init__.py
persuader_technology_automata_data_stream-0.2.5.dist-info/LICENSE
persuader_technology_automata_data_stream-0.2.5.dist-info/METADATA
persuader_technology_automata_data_stream-0.2.5.dist-info/WHEEL
persuader_technology_automata_data_stream-0.2.5.dist-info/top_level.txt
persuader_technology_automata_data_stream-0.2.5.dist-info/RECORD
