Metadata-Version: 2.1
Name: persuader-technology-automata-data-stream
Version: 0.2.5
Summary: Automata Data Stream
Author: Persuader Technology
Author-email: software@persuader.technology
License: UNLICENSE
Classifier: Programming Language :: Python :: 3
License-File: LICENSE
Requires-Dist: websockets (==10.3)
Requires-Dist: persuader-technology-automata-core (>=0.6.0)
Requires-Dist: persuader-technology-automata-logger (>=0.0.5)
Requires-Dist: persuader-technology-automata-auth (>=0.1.5)
